jasmin_mongo_configuration/__init__.py
jasmin_mongo_configuration/__main__.py
jasmin_mongo_configuration/configurationstreamer.py
jasmin_mongo_configuration/mongodb.py
jasmin_mongo_configuration-0.1.0.dist-info/METADATA
jasmin_mongo_configuration-0.1.0.dist-info/WHEEL
jasmin_mongo_configuration-0.1.0.dist-info/entry_points.txt
jasmin_mongo_configuration-0.1.0.dist-info/licenses/LICENSE
jasmin_mongo_configuration-0.1.0.dist-info/RECORD
