Metadata-Version: 2.1
Name: jasmin_mongo_configuration
Version: 0.1.0
Summary: Links Jasmin SMS Gateway to MongoDB cluster's Change Stream (can be one node).
Project-URL: Homepage, https://github.com/BlackOrder/jasmin_mongo_configuration
Project-URL: Bug Tracker, https://github.com/BlackOrder/jasmin_mongo_configuration/issues
Author-email: BlackOrder <4302157+BlackOrder@users.noreply.github.com>
License-File: LICENSE
Classifier: License :: OSI Approved :: GNU General Public License v3 (GPLv3)
Classifier: Operating System :: OS Independent
Classifier: Programming Language :: Python :: 3
Requires-Python: >=3.11
Requires-Dist: dnspython
Requires-Dist: jasmin-telnet
Requires-Dist: pymongo
